easyapi/__init__.py
easyapi/core.py
easyapi_leozhang-0.1.0.dist-info/METADATA
easyapi_leozhang-0.1.0.dist-info/WHEEL
easyapi_leozhang-0.1.0.dist-info/top_level.txt
easyapi_leozhang-0.1.0.dist-info/RECORD
