Metadata-Version: 2.4
Name: easyapi-leozhang
Version: 0.1.0
Summary: A simple unified interface for major AI APIs.
Author: Your Name
Author-email: youremail@example.com
Classifier: Programming Language :: Python :: 3
Classifier: License :: OSI Approved :: MIT License
Requires-Python: >=3.7
Requires-Dist: requests
Requires-Dist: google-generativeai
Requires-Dist: cohere
Dynamic: author
Dynamic: author-email
Dynamic: classifier
Dynamic: requires-dist
Dynamic: requires-python
Dynamic: summary
